mktoolkit/__init__.py
mktoolkit/mktoolkit.py
mktoolkit/segmentation_models/__init__.py
mktoolkit/segmentation_models/__version__.py
mktoolkit/segmentation_models/base/__init__.py
mktoolkit/segmentation_models/base/heads.py
mktoolkit/segmentation_models/base/initialization.py
mktoolkit/segmentation_models/base/model.py
mktoolkit/segmentation_models/base/modules.py
mktoolkit/segmentation_models/encoders/__init__.py
mktoolkit/segmentation_models/encoders/_base.py
mktoolkit/segmentation_models/encoders/_preprocessing.py
mktoolkit/segmentation_models/encoders/_utils.py
mktoolkit/segmentation_models/encoders/densenet.py
mktoolkit/segmentation_models/encoders/dpn.py
mktoolkit/segmentation_models/encoders/efficientnet.py
mktoolkit/segmentation_models/encoders/inceptionresnetv2.py
mktoolkit/segmentation_models/encoders/inceptionv4.py
mktoolkit/segmentation_models/encoders/mobilenet.py
mktoolkit/segmentation_models/encoders/resnet.py
mktoolkit/segmentation_models/encoders/senet.py
mktoolkit/segmentation_models/encoders/timm_efficientnet.py
mktoolkit/segmentation_models/encoders/vgg.py
mktoolkit/segmentation_models/encoders/xception.py
mktoolkit/segmentation_models/unet/__init__.py
mktoolkit/segmentation_models/unet/decoder.py
mktoolkit/segmentation_models/unet/model.py
mktoolkit/segmentation_models/utils/__init__.py
mktoolkit/segmentation_models/utils/base.py
mktoolkit/segmentation_models/utils/functional.py
mktoolkit/segmentation_models/utils/losses.py
mktoolkit/segmentation_models/utils/meter.py
mktoolkit/segmentation_models/utils/metrics.py
mktoolkit/segmentation_models/utils/train.py
mktoolkit/test_mktoolkit.py
mktoolkit-0.0.3.dist-info/METADATA
mktoolkit-0.0.3.dist-info/WHEEL
mktoolkit-0.0.3.dist-info/RECORD
