Metadata-Version: 2.1
Name: mktoolkit
Version: 0.0.3
Summary: 
Author: UEF Cancer
Author-email: uef.cancergroup@gmail.com
Requires-Python: >=3.8,<4.0
Classifier: Programming Language :: Python :: 3
Classifier: Programming Language :: Python :: 3.8
Classifier: Programming Language :: Python :: 3.9
Classifier: Programming Language :: Python :: 3.10
Classifier: Programming Language :: Python :: 3.11
Requires-Dist: Pillow (==9.5.0)
Requires-Dist: efficientnet_pytorch (==0.7.1)
Requires-Dist: numpy (==1.24.2)
Requires-Dist: pretrainedmodels (==0.7.4)
Requires-Dist: pydicom (==2.3.1)
Requires-Dist: requests (==2.28.2)
Requires-Dist: scikit-image (==0.20.0)
Requires-Dist: timm (==0.6.12)
Requires-Dist: torch (==2.0.0)
Requires-Dist: torchvision (==0.15.1)
Requires-Dist: tqdm (==4.65.0)
